[
  {
    "Name": "آب معدنی میوا - ۱٫۵ لیتر بسته ۶ عددی ",
    "Price": "90000",
    "Discount": "0",
    "Link": "https://www.digikala.com/fresh/product/dkp-3439306/",
    "Incredible": "0"
  },
  {
    "Name": "شمش طلا ۲۴ عیار پارسیس مدل 01",
    "Price": "16095000",
    "Discount": "2",
    "Link": "https://www.digikala.com/product/dkp-9565621/",
    "Incredible": "0"
  },
  {
    "Name": "گوشی اپل iPhone 16 Pro Max",
    "Price": "195800000",
    "Discount": "0",
    "Link": "https://www.digikala.com/product/dkp-17986675/",
    "Incredible": "0"
  },
  {
    "Name": "آینه بغل پراید",
    "Price": "358000",
    "Discount": "0",
    "Link": "https://www.digikala.com/product/dkp-6180864/",
    "Incredible": "0"
  },
  {
    "Name": "بخاری برقی پارس خزر",
    "Price": "2557600",
    "Discount": "11",
    "Link": "https://www.digikala.com/product/dkp-3986553/",
    "Incredible": "0"
  },
  {
    "Name": "برنج هاشمی گیلان رفتاری - ۱۰ کیلوگرم",
    "Price": "3447050",
    "Discount": "0",
    "Link": "https://www.digikala.com/fresh/product/dkp-19978231/",
    "Incredible": "0"
  },
  {
    "Name": "مغز پسته خام رویال - ۱ کیلوگرم",
    "Price": "3054060",
    "Discount": "6",
    "Link": "https://www.digikala.com/product/dkp-6182796/",
    "Incredible": "0"
  },
  {
    "Name": "پنیر پیتزا رنده شده کالین - ۱ کیلوگرم",
    "Price": "527850",
    "Discount": "10",
    "Link": "https://www.digikala.com/fresh/product/dkp-1023378/",
    "Incredible": "0"
  },
  {
    "Name": "پنیر فتا دوشه هراز- ۴۰۰ گرم",
    "Price": "96900",
    "Discount": "0",
    "Link": "https://www.digikala.com/fresh/product/dkp-1485597/",
    "Incredible": "0"
  },
  {
    "Name": "پوشک بچه هانیز",
    "Price": "367500",
    "Discount": "0",
    "Link": "https://www.digikala.com/fresh/product/dkp-7932748/",
    "Incredible": "0"
  },
  {
    "Name": "پوشک مولفیکس سایز ۴",
    "Price": "351400",
    "Discount": "0",
    "Link": "https://www.digikala.com/fresh/product/dkp-3765912/",
    "Incredible": "0"
  },
  {
    "Name": "تخم مرغ Fresh بسته ۲۰ عددی گرید A ",
    "Price": "191800",
    "Discount": "0",
    "Link": "https://www.digikala.com/fresh/product/dkp-17729012/",
    "Incredible": "0"
  },
  {
    "Name": "ترازو دیجیتال کمری فیت",
    "Price": "650000",
    "Discount": "16",
    "Link": "https://www.digikala.com/product/dkp-1787072/",
    "Incredible": "0"
  },
  {
    "Name": "تشک دو نفره رویا مدل اولترا ۳",
    "Price": "21260000",
    "Discount": "0",
    "Link": "https://www.digikala.com/product/dkp-188227/",
    "Incredible": "0"
  },
  {
    "Name": "تلفن بی‌سیم پاناسونیک",
    "Price": "3450000",
    "Discount": "0",
    "Link": "https://www.digikala.com/product/dkp-14762/",
    "Incredible": "0"
  },
  {
    "Name": "تلویزیون ال ای دی هوشمند ایکس ویژن ۵۵ اینچ",
    "Price": "35640000",
    "Discount": "20",
    "Link": "https://www.digikala.com/product/dkp-8502180/",
    "Incredible": "0"
  },
  {
    "Name": "تونر پاک کننده صورت لافارر",
    "Price": "186500",
    "Discount": "36",
    "Link": "https://www.digikala.com/product/dkp-4012333/",
    "Incredible": "0"
  },
  {
    "Name": "جعبه ابزار ۱۲۵ عددی",
    "Price": "4880000",
    "Discount": "0",
    "Link": "https://www.digikala.com/product/dkp-4858835/",
    "Incredible": "0"
  },
  {
    "Name": "چای سیاه گلستان مدل ممتاز هندوستان - ۵۰۰ گرم",
    "Price": "500160",
    "Discount": "13",
    "Link": "https://www.digikala.com/fresh/product/dkp-581175/",
    "Incredible": "1"
  },
  {
    "Name": "خیارشور درجه یک مکنزی - ۶۶۰ گرم",
    "Price": "113000",
    "Discount": "0",
    "Link": "https://www.digikala.com/fresh/product/dkp-6293548/",
    "Incredible": "0"
  },
  {
    "Name": "دوربین دیجیتال کانن مدل EOS 5D Mark IV",
    "Price": "187000000",
    "Discount": "0",
    "Link": "https://www.digikala.com/product/dkp-170831/",
    "Incredible": "0"
  },
  {
    "Name": "گوشی خورشتی بدون استخوان گوسفند مهیا پروتئین - ۱ کیلوگرم",
    "Price": "1255000",
    "Discount": "2",
    "Link": "https://www.digikala.com/fresh/product/dkp-792421/",
    "Incredible": "1"
  },
  {
    "Name": "رژ لب جامد الیزا مدل Mini",
    "Price": "74000",
    "Discount": "26",
    "Link": "https://www.digikala.com/product/dkp-2578874/",
    "Incredible": "0"
  },
  {
    "Name": "روغن آفتابگردان غنچه پلاس - ۹۰۰ میلی لیتر",
    "Price": "72600",
    "Discount": "0",
    "Link": "https://www.digikala.com/fresh/product/dkp-8511786/",
    "Incredible": "0"
  },
  {
    "Name": "زیرپوش رکابی مردانه امیدنو",
    "Price": "100600",
    "Discount": "42",
    "Link": "https://www.digikala.com/product/dkp-5741395/",
    "Incredible": "0"
  },
  {
    "Name": "ژل شستشوی صورت لافارر",
    "Price": "631900",
    "Discount": "0",
    "Link": "https://www.digikala.com/product/dkp-515367/",
    "Incredible": "0"
  },
  {
    "Name": "ساعت هوشمند مدل T900 Pro Max",
    "Price": "680000",
    "Discount": "0",
    "Link": "https://www.digikala.com/product/dkp-12510113/",
    "Incredible": "0"
  },
  {
    "Name": "سرویس غذاخوری ۳۰ پارچه ۶ نفره",
    "Price": "2899000",
    "Discount": "0",
    "Link": "https://www.digikala.com/product/dkp-2323723/",
    "Incredible": "0"
  },
  {
    "Name": "سیب‌زمینی نیمه آماده باتو - ۷۵۰ گرم",
    "Price": "165000",
    "Discount": "0",
    "Link": "https://www.digikala.com/fresh/product/dkp-8307752/",
    "Incredible": "0"
  },
  {
    "Name": "ران مرغ بی پوست مهیا پروتئین - ۹۰۰ گرم",
    "Price": "208800",
    "Discount": "0",
    "Link": "https://www.digikala.com/fresh/product/dkp-792129/",
    "Incredible": "0"
  },
  {
    "Name": "شومیز زنانه",
    "Price": "650000",
    "Discount": "0",
    "Link": "https://www.digikala.com/product/dkp-19228001/",
    "Incredible": "0"
  },
  {
    "Name": "عسل سنتی چند گیاه زنبورداران - ۱۰۰۰ گرم",
    "Price": "575000",
    "Discount": "0",
    "Link": "https://www.digikala.com/product/dkp-18041116/",
    "Incredible": "0"
  },
  {
    "Name": "عطر مردانه ساواج دیور ۱۰۰ میلی لیتر",
    "Price": "497000",
    "Discount": "17",
    "Link": "https://www.digikala.com/product/dkp-7608527/",
    "Incredible": "0"
  },
  {
    "Name": "غذای خشک گربه ۲ کیلوگرم ",
    "Price": "395990",
    "Discount": "0",
    "Link": "https://www.digikala.com/product/dkp-3540612/",
    "Incredible": "0"
  },
  {
    "Name": "فلش مموری کوئین تک - ۶۴ گیگ",
    "Price": "448000",
    "Discount": "2",
    "Link": "https://www.digikala.com/product/dkp-9089262/",
    "Incredible": "0"
  },
  {
    "Name": "دان فلفل سیاه آسیابی گلها - ۴۰ گرم",
    "Price": "128500",
    "Discount": "10",
    "Link": "https://www.digikala.com/fresh/product/dkp-5063955/",
    "Incredible": "0"
  },
  {
    "Name": "قرص ماشین ظرفشویی هوم پلاس ۲۴ عددی",
    "Price": "307400",
    "Discount": "0",
    "Link": "https://www.digikala.com/fresh/product/dkp-3431048/",
    "Incredible": "0"
  },
  {
    "Name": "کپسول آتش نشانی دریا ۳ کیلوگرم",
    "Price": "685000",
    "Discount": "0",
    "Link": "https://www.digikala.com/product/dkp-4804773/",
    "Incredible": "0"
  },
  {
    "Name": "کتاب هر دو در نهایت می میرند",
    "Price": "125000",
    "Discount": "69",
    "Link": "https://www.digikala.com/product/dkp-11602682/",
    "Incredible": "0"
  },
  {
    "Name": "کره حیوانی پاستوریزه رامک ۱۰۰ گرم",
    "Price": "73000",
    "Discount": "0",
    "Link": "https://www.digikala.com/fresh/product/dkp-1513096/",
    "Incredible": "0"
  },
  {
    "Name": "کفش پیاده روی مردانه",
    "Price": "260000",
    "Discount": "35",
    "Link": "https://www.digikala.com/product/dkp-4262387/",
    "Incredible": "0"
  },
  {
    "Name": "کنسرو ماهی تن در روغن مایع شیلتون - ۱۸۰ گرم",
    "Price": "119900",
    "Discount": "0",
    "Link": "https://www.digikala.com/fresh/product/dkp-1888876/",
    "Incredible": "0"
  },
  {
    "Name": "کنسول Playstation 5",
    "Price": "53199000",
    "Discount": "5",
    "Link": "https://www.digikala.com/product/dkp-13867812/",
    "Incredible": "1"
  },
  {
    "Name": "کیف کمری چرمی",
    "Price": "1177000",
    "Discount": "0",
    "Link": "https://www.digikala.com/product/dkp-7963070/",
    "Incredible": "0"
  },
  {
    "Name": "گوشی موبایل شیائومی مدل Redmi Note 14 4G",
    "Price": "17449000",
    "Discount": "0",
    "Link": "https://www.digikala.com/product/dkp-17580036/",
    "Incredible": "0"
  },
  {
    "Name": "لپ تاپ 15.6 اینچی اچ‌پی G10 255",
    "Price": "34800000",
    "Discount": "0",
    "Link": "https://www.digikala.com/product/dkp-16009593/",
    "Incredible": "0"
  },
  {
    "Name": "ماشین لباسشویی ۹ کیلوگرمی دوو",
    "Price": "47100000",
    "Discount": "0",
    "Link": "https://www.digikala.com/product/dkp-18889150/",
    "Incredible": "0"
  },
  {
    "Name": "ماکارونی پنه زر ماکارون ۵۰۰ گرم",
    "Price": "45000",
    "Discount": "0",
    "Link": "https://www.digikala.com/fresh/product/dkp-633507/",
    "Incredible": "0"
  },
  {
    "Name": "موتور برق آسترا",
    "Price": "14700000",
    "Discount": "0",
    "Link": "https://www.digikala.com/product/dkp-9192254/",
    "Incredible": "0"
  },
  {
    "Name": "نوشابه  پپسی - ۱٫۵ لیتر بسته ۶ عددی",
    "Price": "287700",
    "Discount": "0",
    "Link": "https://www.digikala.com/fresh/product/dkp-1923615/",
    "Incredible": "0"
  },
  {
    "Name": "نیم‌بوت زنانه چرم مشهد",
    "Price": "17498000",
    "Discount": "0",
    "Link": "https://www.digikala.com/product/dkp-13025578/",
    "Incredible": "0"
  },
  {
    "Name": "هارد اکسترنال وسترن دیجیتال ۱ ترابایت",
    "Price": "8545100",
    "Discount": "0",
    "Link": "https://www.digikala.com/product/dkp-2309086/",
    "Incredible": "0"
  },
  {
    "Name": "هندزفری QKZ",
    "Price": "285000",
    "Discount": "0",
    "Link": "https://www.digikala.com/product/dkp-2891227/",
    "Incredible": "0"
  },
  {
    "Name": "ویدئو پروژکتور T6 Max",
    "Price": "26500000",
    "Discount": "0",
    "Link": "https://www.digikala.com/product/dkp-7717879/",
    "Incredible": "0"
  },
  {
    "Name": "یخچال و فریزر ایستکول",
    "Price": "20735700",
    "Discount": "14",
    "Link": "https://www.digikala.com/product/dkp-15113124/",
    "Incredible": "0"
  },
  {
    "Name": "کرم ضدآفتاب لافارر",
    "Price": "819800",
    "Discount": "0",
    "Link": "https://www.digikala.com/product/dkp-714982/",
    "Incredible": "0"
  }
]